[
    {
        "actor_label": "Cube2",
        "actor_location": [
            2374.1663050926227,
            429.8404095152064,
            660.6431987329497
        ],
        "actor_size": [
            90.33423667569969,
            25.5947003914481,
            133.99578440228856
        ],
        "materials": [
            "windowMaterial"
        ]
    },
    {
        "actor_label": "Cube3",
        "actor_location": [
            2179.947696239867,
            706.5690298197821,
            799.6536002105427
        ],
        "actor_size": [
            25.0,
            52.7661007143754,
            81.0992799341816
        ],
        "materials": [
            "windowMaterial"
        ]
    },
    {
        "actor_label": "Cube4",
        "actor_location": [
            2232.6426676340257,
            429.8404095152064,
            660.6431987329497
        ],
        "actor_size": [
            90.33423667569969,
            25.5947003914481,
            133.99578440228856
        ],
        "materials": [
            "windowMaterial"
        ]
    },
    {
        "actor_label": "Cube5",
        "actor_location": [
            1719.243089193797,
            599.0748446417098,
            799.6536002105427
        ],
        "actor_size": [
            25.0,
            52.754245827672776,
            81.0992799341816
        ],
        "materials": [
            "windowMaterial"
        ]
    },
    {
        "actor_label": "Cube6",
        "actor_location": [
            2110.8455616489678,
            529.9608551641069,
            799.6536002105427
        ],
        "actor_size": [
            52.754245827673,
            25.0,
            81.0992799341816
        ],
        "materials": [
            "windowMaterial"
        ]
    },
    {
        "actor_label": "Cube7",
        "actor_location": [
            2861.1531959589065,
            572.0871950626768,
            323.02788032254773
        ],
        "actor_size": [
            25.0,
            178.07225316347626,
            180.5617793710744
        ],
        "materials": [
            "windowMaterial"
        ]
    },
    {
        "actor_label": "Cube8",
        "actor_location": [
            1788.3570786713997,
            529.9608551641069,
            799.6536002105427
        ],
        "actor_size": [
            52.75424582767255,
            25.0,
            81.0992799341816
        ],
        "materials": [
            "windowMaterial"
        ]
    },
    {
        "actor_label": "Cube9",
        "actor_location": [
            2515.6899425512197,
            429.8404095152064,
            660.6431987329497
        ],
        "actor_size": [
            90.33423667569969,
            25.5947003914481,
            133.99578440228856
        ],
        "materials": [
            "windowMaterial"
        ]
    },
    {
        "actor_label": "Cube10",
        "actor_location": [
            1666.5481177996385,
            429.8404095152064,
            660.6431987329497
        ],
        "actor_size": [
            90.33423667570014,
            25.5947003914481,
            133.99578440228856
        ],
        "materials": [
            "windowMaterial"
        ]
    },
    {
        "actor_label": "Cube11",
        "actor_location": [
            1525.0244803410417,
            429.8404095152064,
            660.6431987329497
        ],
        "actor_size": [
            90.33423667570014,
            25.5947003914481,
            133.99578440228856
        ],
        "materials": [
            "windowMaterial"
        ]
    },
    {
        "actor_label": "Cube12",
        "actor_location": [
            1383.5008428824447,
            429.8404095152064,
            660.6431987329497
        ],
        "actor_size": [
            90.33423667569969,
            25.5947003914481,
            133.99578440228856
        ],
        "materials": [
            "windowMaterial"
        ]
    },
    {
        "actor_label": "Cube13",
        "actor_location": [
            1659.7789774923126,
            1091.5386931647095,
            660.157148378133
        ],
        "actor_size": [
            72.26738934055948,
            25.0,
            115.85780774693126
        ],
        "materials": [
            "windowMaterial"
        ]
    },
    {
        "actor_label": "Cube14",
        "actor_location": [
            2614.660464189944,
            683.8017199069631,
            660.1927130382415
        ],
        "actor_size": [
            25.594700391447986,
            90.33423667570014,
            133.99578440228856
        ],
        "materials": [
            "windowMaterial"
        ]
    },
    {
        "actor_label": "Cube15",
        "actor_location": [
            1719.243089193797,
            706.5690298197821,
            799.6536002105427
        ],
        "actor_size": [
            25.0,
            52.7661007143754,
            81.0992799341816
        ],
        "materials": [
            "windowMaterial"
        ]
    },
    {
        "actor_label": "Cube16",
        "actor_location": [
            2614.660464189944,
            838.3775876253949,
            660.1927130382415
        ],
        "actor_size": [
            25.594700391447986,
            90.33423667570014,
            133.99578440228856
        ],
        "materials": [
            "windowMaterial"
        ]
    },
    {
        "actor_label": "Cube17",
        "actor_location": [
            2614.660464189944,
            992.9534553438273,
            660.1927130382415
        ],
        "actor_size": [
            25.594700391447986,
            90.33423667569969,
            133.99578440228856
        ],
        "materials": [
            "windowMaterial"
        ]
    },
    {
        "actor_label": "Cube18",
        "actor_location": [
            2614.660464189944,
            529.2377070752334,
            660.1927130382415
        ],
        "actor_size": [
            25.594700391447986,
            90.33423667570014,
            133.99578440228856
        ],
        "materials": [
            "windowMaterial"
        ]
    },
    {
        "actor_label": "Cube19",
        "actor_location": [
            2091.1190301754286,
            429.8404095152064,
            660.6431987329497
        ],
        "actor_size": [
            90.3342366757006,
            25.5947003914481,
            133.99578440228856
        ],
        "materials": [
            "windowMaterial"
        ]
    },
    {
        "actor_label": "Cube20",
        "actor_location": [
            1949.5953927168318,
            429.8404095152064,
            660.6431987329497
        ],
        "actor_size": [
            90.33423667570014,
            25.5947003914481,
            133.99578440228856
        ],
        "materials": [
            "windowMaterial"
        ]
    },
    {
        "actor_label": "Cube21",
        "actor_location": [
            1808.0717552582353,
            429.8404095152064,
            660.6431987329497
        ],
        "actor_size": [
            90.33423667570014,
            25.5947003914481,
            133.99578440228856
        ],
        "materials": [
            "windowMaterial"
        ]
    },
    {
        "actor_label": "Cube22",
        "actor_location": [
            1284.8859678448055,
            992.1710328214392,
            660.1927130382415
        ],
        "actor_size": [
            25.59470039144844,
            90.33423667570003,
            133.99578440228856
        ],
        "materials": [
            "windowMaterial"
        ]
    },
    {
        "actor_label": "Cube23",
        "actor_location": [
            1127.2278295836327,
            226.4639006845011,
            323.02788032254773
        ],
        "actor_size": [
            108.03358252305179,
            25.0,
            180.5617793710744
        ],
        "materials": [
            "windowMaterial"
        ]
    },
    {
        "actor_label": "Cube24",
        "actor_location": [
            1284.8859678448055,
            683.0311522712777,
            660.1927130382415
        ],
        "actor_size": [
            25.59470039144844,
            90.33423667569946,
            133.99578440228856
        ],
        "materials": [
            "windowMaterial"
        ]
    },
    {
        "actor_label": "Cube25",
        "actor_location": [
            1284.8859678448055,
            528.4552845528455,
            660.1927130382415
        ],
        "actor_size": [
            25.59470039144844,
            90.33423667570014,
            133.99578440228856
        ],
        "materials": [
            "windowMaterial"
        ]
    },
    {
        "actor_label": "Cube26",
        "actor_location": [
            1788.3570786713997,
            990.6654622101778,
            799.6536002105427
        ],
        "actor_size": [
            52.75424582767255,
            25.0,
            81.0992799341816
        ],
        "materials": [
            "windowMaterial"
        ]
    },
    {
        "actor_label": "Cube27",
        "actor_location": [
            2581.7216614860813,
            217.33563792330835,
            323.02788032254773
        ],
        "actor_size": [
            100.93250538804568,
            25.0,
            180.5617793710744
        ],
        "materials": [
            "windowMaterial"
        ]
    },
    {
        "actor_label": "Cube28",
        "actor_location": [
            2110.8455616489678,
            990.6654622101778,
            799.6536002105427
        ],
        "actor_size": [
            52.754245827673,
            25.0,
            81.0992799341816
        ],
        "materials": [
            "windowMaterial"
        ]
    },
    {
        "actor_label": "Cube29",
        "actor_location": [
            1895.8453364061204,
            529.9608551641069,
            799.6536002105427
        ],
        "actor_size": [
            52.75424582767255,
            25.0,
            81.0992799341816
        ],
        "materials": [
            "windowMaterial"
        ]
    },
    {
        "actor_label": "Cube30",
        "actor_location": [
            1517.129125796945,
            1091.5386931647095,
            660.157148378133
        ],
        "actor_size": [
            72.26738934055993,
            25.0,
            115.85780774693126
        ],
        "materials": [
            "windowMaterial"
        ]
    },
    {
        "actor_label": "Cube31",
        "actor_location": [
            1010.9373184720477,
            572.0871950626768,
            323.02788032254773
        ],
        "actor_size": [
            25.0,
            178.07225316347626,
            180.5617793710744
        ],
        "materials": [
            "windowMaterial"
        ]
    },
    {
        "actor_label": "Cube32",
        "actor_location": [
            1719.243089193797,
            814.0632149978542,
            799.6536002105427
        ],
        "actor_size": [
            25.0,
            52.75424582767232,
            81.0992799341816
        ],
        "materials": [
            "windowMaterial"
        ]
    },
    {
        "actor_label": "Cube33",
        "actor_location": [
            1374.4674192148748,
            1091.5386931647095,
            660.157148378133
        ],
        "actor_size": [
            72.26738934055993,
            25.0,
            115.85780774693126
        ],
        "materials": [
            "windowMaterial"
        ]
    },
    {
        "actor_label": "Cube34",
        "actor_location": [
            1010.9373184720477,
            1005.6915311060372,
            323.02788032254773
        ],
        "actor_size": [
            25.0,
            178.07225316347683,
            180.5617793710744
        ],
        "materials": [
            "windowMaterial"
        ]
    },
    {
        "actor_label": "Cube35",
        "actor_location": [
            1895.8453364061204,
            990.6654622101778,
            799.6536002105427
        ],
        "actor_size": [
            52.75424582767255,
            25.0,
            81.0992799341816
        ],
        "materials": [
            "windowMaterial"
        ]
    },
    {
        "actor_label": "Cube36",
        "actor_location": [
            2861.1531959589065,
            1005.6915311060372,
            323.02788032254773
        ],
        "actor_size": [
            25.0,
            178.07225316347683,
            180.5617793710744
        ],
        "materials": [
            "windowMaterial"
        ]
    },
    {
        "actor_label": "Cube37",
        "actor_location": [
            1945.078680883047,
            1091.5386931647095,
            660.157148378133
        ],
        "actor_size": [
            72.26738934055993,
            25.0,
            115.85780774693126
        ],
        "materials": [
            "windowMaterial"
        ]
    },
    {
        "actor_label": "Cube38",
        "actor_location": [
            2179.947696239867,
            921.5633276192777,
            799.6536002105427
        ],
        "actor_size": [
            25.0,
            52.75424582767255,
            81.0992799341816
        ],
        "materials": [
            "windowMaterial"
        ]
    },
    {
        "actor_label": "Cube39",
        "actor_location": [
            2003.345449027544,
            990.6654622101778,
            799.6536002105427
        ],
        "actor_size": [
            52.75424582767255,
            25.0,
            81.0992799341816
        ],
        "materials": [
            "windowMaterial"
        ]
    },
    {
        "actor_label": "Cube40",
        "actor_location": [
            2373.0400908558518,
            1091.5386931647095,
            660.157148378133
        ],
        "actor_size": [
            72.26738934055993,
            25.0,
            115.85780774693126
        ],
        "materials": [
            "windowMaterial"
        ]
    },
    {
        "actor_label": "Cube41",
        "actor_location": [
            1802.42882918768,
            1091.5386931647095,
            660.157148378133
        ],
        "actor_size": [
            72.26738934056038,
            25.0,
            115.85780774693126
        ],
        "materials": [
            "windowMaterial"
        ]
    },
    {
        "actor_label": "Cube42",
        "actor_location": [
            1283.3329776867324,
            226.4639006845011,
            323.02788032254773
        ],
        "actor_size": [
            108.03358252305179,
            25.0,
            180.5617793710744
        ],
        "materials": [
            "windowMaterial"
        ]
    },
    {
        "actor_label": "Cube43",
        "actor_location": [
            2179.947696239867,
            599.0748446417098,
            799.6536002105427
        ],
        "actor_size": [
            25.0,
            52.754245827672776,
            81.0992799341816
        ],
        "materials": [
            "windowMaterial"
        ]
    },
    {
        "actor_label": "Cube44",
        "actor_location": [
            2727.5664051478666,
            217.33563792330835,
            323.02788032254773
        ],
        "actor_size": [
            100.92065050134352,
            25.0,
            180.5617793710744
        ],
        "materials": [
            "windowMaterial"
        ]
    },
    {
        "actor_label": "Cube45",
        "actor_location": [
            2087.7403874651172,
            1091.5386931647095,
            660.157148378133
        ],
        "actor_size": [
            72.26738934055993,
            25.0,
            115.85780774693126
        ],
        "materials": [
            "windowMaterial"
        ]
    },
    {
        "actor_label": "Cube46",
        "actor_location": [
            2179.947696239867,
            814.0632149978542,
            799.6536002105427
        ],
        "actor_size": [
            25.0,
            52.75424582767232,
            81.0992799341816
        ],
        "materials": [
            "windowMaterial"
        ]
    },
    {
        "actor_label": "Cube47",
        "actor_location": [
            2515.6899425512197,
            1091.5386931647095,
            660.157148378133
        ],
        "actor_size": [
            72.26738934055993,
            25.0,
            115.85780774693126
        ],
        "materials": [
            "windowMaterial"
        ]
    },
    {
        "actor_label": "Cube48",
        "actor_location": [
            1284.8859678448055,
            837.60701998971,
            660.1927130382415
        ],
        "actor_size": [
            25.59470039144844,
            90.33423667570014,
            133.99578440228856
        ],
        "materials": [
            "windowMaterial"
        ]
    },
    {
        "actor_label": "Cube49",
        "actor_location": [
            1719.243089193797,
            921.5633276192777,
            799.6536002105427
        ],
        "actor_size": [
            25.0,
            52.75424582767255,
            81.0992799341816
        ],
        "materials": [
            "windowMaterial"
        ]
    },
    {
        "actor_label": "Cube50",
        "actor_location": [
            2003.345449027544,
            529.9608551641069,
            799.6536002105427
        ],
        "actor_size": [
            52.75424582767255,
            25.0,
            81.0992799341816
        ],
        "materials": [
            "windowMaterial"
        ]
    },
    {
        "actor_label": "Cube51",
        "actor_location": [
            2230.3902391604847,
            1091.5386931647095,
            660.157148378133
        ],
        "actor_size": [
            72.26738934055993,
            25.0,
            115.85780774693126
        ],
        "materials": [
            "windowMaterial"
        ]
    },
    {
        "actor_label": "Cube52",
        "actor_location": [
            2655.5402105902076,
            1647.1046430849262,
            501.33694670280033
        ],
        "actor_size": [
            425.0,
            650.0,
            50.0
        ],
        "materials": [
            "roofMaterial"
        ]
    },
    {
        "actor_label": "Cube53",
        "actor_location": [
            1949.6013201601836,
            760.319086130494,
            751.2797350195724
        ],
        "actor_size": [
            1475.0,
            800.0,
            25.0
        ],
        "materials": [
            "roofMaterial"
        ]
    },
    {
        "actor_label": "Cube54",
        "actor_location": [
            1051.9675697719358,
            1463.6813690971555,
            472.6934658235471
        ],
        "actor_size": [
            750.0,
            1050.0,
            25.0
        ],
        "materials": [
            "roofMaterial"
        ]
    },
    {
        "actor_label": "Cube55",
        "actor_location": [
            1949.595392716832,
            760.3131586871423,
            867.2086720867208
        ],
        "actor_size": [
            599.9999999999998,
            599.9999999999999,
            25.0
        ],
        "materials": [
            "roofMaterial"
        ]
    },
    {
        "actor_label": "Cube56",
        "actor_location": [
            1935.7311027178516,
            1275.6035915564755,
            285.09224287343477
        ],
        "actor_size": [
            326.77995196399957,
            25.0,
            281.1149283846295
        ],
        "materials": [
            "doorMaterial"
        ]
    },
    {
        "actor_label": "Cube57",
        "actor_location": [
            1250.8920802243895,
            1275.6035915564755,
            285.2226466271661
        ],
        "actor_size": [
            158.64209385750928,
            25.0,
            280.8541208771668
        ],
        "materials": [
            "doorMaterial"
        ]
    },
    {
        "actor_label": "Cube58",
        "actor_location": [
            2615.2117164216265,
            1275.6035915564755,
            285.2226466271661
        ],
        "actor_size": [
            170.63923920079196,
            25.0,
            280.8541208771668
        ],
        "materials": [
            "doorMaterial"
        ]
    },
    {
        "actor_label": "Cube60",
        "actor_location": [
            2950.6872277821644,
            1242.3921264584474,
            447.02068440631916
        ],
        "actor_size": [
            219.70661526387812,
            205.91938202846586,
            775.0
        ],
        "materials": [
            "wallMaterial"
        ]
    },
    {
        "actor_label": "Cube64",
        "actor_location": [
            2472.0758143714424,
            1957.2417946401686,
            273.20325203252025
        ],
        "actor_size": [
            63.23396567299005,
            63.23396567299005,
            425.0
        ],
        "materials": [
            "pillarMaterial"
        ]
    },
    {
        "actor_label": "Cube65",
        "actor_location": [
            1392.0147000595116,
            1957.2417946401686,
            263.20325203252025
        ],
        "actor_size": [
            63.23396567299005,
            63.23396567299005,
            400.0
        ],
        "materials": [
            "pillarMaterial"
        ]
    },
    {
        "actor_label": "Cube66",
        "actor_location": [
            1945.6062233413238,
            759.1158151301548,
            978.9824713645212
        ],
        "actor_size": [
            238.27136784053755,
            238.2832227272404,
            170.4614159002482
        ],
        "materials": [
            "roofMaterial"
        ]
    },
    {
        "actor_label": "Cube67",
        "actor_location": [
            1934.6013199999998,
            796.319086,
            591.279735
        ],
        "actor_size": [
            2024.9999999999998,
            1175.0,
            25.0
        ],
        "materials": [
            "roofMaterial"
        ]
    },
    {
        "actor_label": "Cube68",
        "actor_location": [
            1949.595393,
            760.313159,
            804.208672
        ],
        "actor_size": [
            500.0,
            475.0,
            100.0
        ],
        "materials": [
            "wallMaterial"
        ]
    },
    {
        "actor_label": "Cube69",
        "actor_location": [
            1949.6013199999998,
            760.319086,
            670.279735
        ],
        "actor_size": [
            1374.9999999999998,
            700.0,
            150.0
        ],
        "materials": [
            "wallMaterial"
        ]
    },
    {
        "actor_label": "Cube70",
        "actor_location": [
            1934.6013199999998,
            751.319086,
            320.27973499999996
        ],
        "actor_size": [
            1874.9999999999998,
            1075.0,
            525.0
        ],
        "materials": [
            "wallMaterial"
        ]
    },
    {
        "actor_label": "Cube63",
        "actor_location": [
            864.96757,
            1463.681369,
            263.693466
        ],
        "actor_size": [
            375.0,
            1050.0,
            400.0
        ],
        "materials": [
            "wallMaterial"
        ]
    },
    {
        "actor_label": "Cube71",
        "actor_location": [
            2833.075814,
            1957.241795,
            273.203252
        ],
        "actor_size": [
            63.23400000000038,
            63.233999999999924,
            425.0
        ],
        "materials": [
            "pillarMaterial"
        ]
    },
    {
        "actor_label": "Cube72",
        "actor_location": [
            2950.6872277821644,
            1242.3921264584474,
            1388.859251672132
        ],
        "actor_size": [
            219.70661526387812,
            205.91938202846586,
            1136.6465370690457
        ],
        "materials": [
            "roofMaterial"
        ]
    }
]