[
    {
        "actor_label": "Cube2",
        "actor_location": [
            2209.487111983342,
            2439.1259603187905,
            528.8753799392099
        ],
        "actor_size": [
            91.18541033434667,
            25.0,
            218.84498480243155
        ],
        "materials": [
            "windowMaterial"
        ]
    },
    {
        "actor_label": "Cube3",
        "actor_location": [
            1755.0798171505157,
            1536.3903980087598,
            527.355623100304
        ],
        "actor_size": [
            182.3708206686929,
            25.0,
            221.8844984802431
        ],
        "materials": [
            "windowMaterial"
        ]
    },
    {
        "actor_label": "Cube4",
        "actor_location": [
            2511.9187229255917,
            880.6093387262769,
            528.8753799392099
        ],
        "actor_size": [
            25.0,
            91.18541033434644,
            218.84498480243155
        ],
        "materials": [
            "windowMaterial"
        ]
    },
    {
        "actor_label": "Cube5",
        "actor_location": [
            1010.3989660866858,
            1536.3903980087598,
            528.8753799392099
        ],
        "actor_size": [
            182.3708206686931,
            25.0,
            218.84498480243155
        ],
        "materials": [
            "windowMaterial"
        ]
    },
    {
        "actor_label": "Cube6",
        "actor_location": [
            2511.9187229255917,
            1257.5090347749085,
            528.8753799392099
        ],
        "actor_size": [
            25.0,
            91.18541033434667,
            218.84498480243155
        ],
        "materials": [
            "windowMaterial"
        ]
    },
    {
        "actor_label": "Cube8",
        "actor_location": [
            1986.0828566641935,
            1536.3903980087598,
            527.355623100304
        ],
        "actor_size": [
            182.3708206686931,
            25.0,
            221.8844984802431
        ],
        "materials": [
            "windowMaterial"
        ]
    },
    {
        "actor_label": "Cube12",
        "actor_location": [
            688.2105162386612,
            2901.50300361391,
            528.8753799392099
        ],
        "actor_size": [
            25.0,
            182.37082066869334,
            218.84498480243155
        ],
        "materials": [
            "windowMaterial"
        ]
    },
    {
        "actor_label": "Cube13",
        "actor_location": [
            688.2105162386612,
            1858.5788478567843,
            528.8753799392099
        ],
        "actor_size": [
            25.0,
            182.3708206686929,
            218.84498480243155
        ],
        "materials": [
            "windowMaterial"
        ]
    },
    {
        "actor_label": "Cube14",
        "actor_location": [
            3412.3686666826216,
            2900.7491084890985,
            528.8753799392099
        ],
        "actor_size": [
            25.0,
            182.37082066869243,
            218.84498480243155
        ],
        "materials": [
            "windowMaterial"
        ]
    },
    {
        "actor_label": "Cube17",
        "actor_location": [
            1587.1407031567858,
            2900.7491084890985,
            528.8753799392099
        ],
        "actor_size": [
            25.0,
            182.37082066869243,
            218.84498480243155
        ],
        "materials": [
            "windowMaterial"
        ]
    },
    {
        "actor_label": "Cube18",
        "actor_location": [
            2217.0858961778713,
            1536.3903980087598,
            527.355623100304
        ],
        "actor_size": [
            182.37082066869243,
            25.0,
            221.8844984802431
        ],
        "materials": [
            "windowMaterial"
        ]
    },
    {
        "actor_label": "Cube19",
        "actor_location": [
            1893.341789723093,
            2439.1259603187905,
            528.8753799392099
        ],
        "actor_size": [
            91.18541033434667,
            25.0,
            218.84498480243155
        ],
        "materials": [
            "windowMaterial"
        ]
    },
    {
        "actor_label": "Cube20",
        "actor_location": [
            2511.9187229255917,
            2901.50300361391,
            528.8753799392099
        ],
        "actor_size": [
            25.0,
            182.37082066869334,
            218.84498480243155
        ],
        "materials": [
            "windowMaterial"
        ]
    },
    {
        "actor_label": "Cube21",
        "actor_location": [
            1139.170321002594,
            2447.3399135261416,
            747.7203647416414
        ],
        "actor_size": [
            960.0000381469727,
            1880.000114440918,
            109.42249240121578
        ],
        "materials": [
            "roofMaterial"
        ]
    },
    {
        "actor_label": "Cube22",
        "actor_location": [
            2511.9187229255917,
            1069.0591867505925,
            501.5197568389058
        ],
        "actor_size": [
            25.0,
            218.8449848024319,
            273.5562310030395
        ],
        "materials": [
            "doorMaterial"
        ]
    },
    {
        "actor_label": "Cube23",
        "actor_location": [
            2051.4324007371415,
            2439.1259603187905,
            501.5197568389058
        ],
        "actor_size": [
            127.65957446808534,
            25.0,
            273.5562310030395
        ],
        "materials": [
            "doorMaterial"
        ]
    },
    {
        "actor_label": "Cube24",
        "actor_location": [
            1138.0585405547708,
            3350.214201948161,
            528.8753799392099
        ],
        "actor_size": [
            583.5866261398173,
            25.0,
            218.84498480243155
        ],
        "materials": [
            "windowMaterial"
        ]
    },
    {
        "actor_label": "Cube15",
        "actor_location": [
            2962.520642366512,
            3351.7339587870674,
            528.8753799392099
        ],
        "actor_size": [
            583.5866261398187,
            25.0,
            218.84498480243155
        ],
        "materials": [
            "windowMaterial"
        ]
    },
    {
        "actor_label": "Cube25",
        "actor_location": [
            1893.3417894898255,
            2677.927570579338,
            421.30936845548115
        ],
        "actor_size": [
            180.00000715255737,
            25.0,
            120.00000476837158
        ],
        "materials": [
            "railingMaterial"
        ]
    },
    {
        "actor_label": "Cube26",
        "actor_location": [
            2216.6578090244425,
            2677.927571,
            421.30936501336265
        ],
        "actor_size": [
            180.0,
            25.0,
            120.0
        ],
        "materials": [
            "railingMaterial"
        ]
    },
    {
        "actor_label": "Cube27",
        "actor_location": [
            2286.4273914926466,
            2560.029973914203,
            421.3093655105891
        ],
        "actor_size": [
            25.000003041991476,
            250.0000003041987,
            120.0
        ],
        "materials": [
            "railingMaterial"
        ]
    },
    {
        "actor_label": "Cube28",
        "actor_location": [
            1810.2890630688987,
            2560.029974,
            421.30936605281835
        ],
        "actor_size": [
            25.000004363323114,
            250.0000004363319,
            120.0
        ],
        "materials": [
            "railingMaterial"
        ]
    },
    {
        "actor_label": "Cube29",
        "actor_location": [
            2051.4324008432322,
            2555.177568146036,
            321.7114511662904
        ],
        "actor_size": [
            520.0000286102295,
            273.5562009734367,
            80.00000452071492
        ],
        "materials": [
            "balconyMaterial"
        ]
    },
    {
        "actor_label": "Cube30",
        "actor_location": [
            2051.4324000386464,
            2748.352005337565,
            321.711451
        ],
        "actor_size": [
            270.0000047683716,
            100.00000139626354,
            80.0000017453292
        ],
        "materials": [
            "stairMaterial"
        ]
    },
    {
        "actor_label": "Cube31",
        "actor_location": [
            2957.8695156697236,
            2462.420338785614,
            747.720365
        ],
        "actor_size": [
            960.0,
            1839.9999618530273,
            109.4224999999999
        ],
        "materials": [
            "roofMaterial"
        ]
    },
    {
        "actor_label": "Cube32",
        "actor_location": [
            3413.298342093674,
            1075.0212801811826,
            747.720365
        ],
        "actor_size": [
            1870.0000879751906,
            960.0000227540941,
            109.4224999999999
        ],
        "materials": [
            "roofMaterial"
        ]
    },
    {
        "actor_label": "Cube33",
        "actor_location": [
            2043.9957933530732,
            1985.8789262268829,
            747.720365
        ],
        "actor_size": [
            860.0000549021333,
            960.0000150098322,
            109.4224999999999
        ],
        "materials": [
            "roofMaterial"
        ]
    },
    {
        "actor_label": "Cube34",
        "actor_location": [
            1139.1703244449975,
            2447.339914,
            492.3876114632369
        ],
        "actor_size": [
            960.0,
            1880.0001000000002,
            400.0
        ],
        "materials": [
            "wallMaterial"
        ]
    },
    {
        "actor_label": "Cube35",
        "actor_location": [
            2957.8695194449974,
            2462.420339,
            492.3876114632369
        ],
        "actor_size": [
            960.0,
            1840.0,
            400.0
        ],
        "materials": [
            "wallMaterial"
        ]
    },
    {
        "actor_label": "Cube36",
        "actor_location": [
            3413.2983454449977,
            1075.02128,
            492.3876114632369
        ],
        "actor_size": [
            1870.0001167551604,
            960.0000326376585,
            400.0
        ],
        "materials": [
            "wallMaterial"
        ]
    },
    {
        "actor_label": "Cube37",
        "actor_location": [
            2043.9957964449977,
            1985.878926,
            492.3876114632369
        ],
        "actor_size": [
            860.0000167551609,
            960.0000150098317,
            400.0
        ],
        "materials": [
            "wallMaterial"
        ]
    }
]