[
    {
        "actor_label": "Cube",
        "actor_location": [
            1312.0,
            1579.69912622499,
            903.2840691193487
        ],
        "actor_size": [
            2600.0,
            3159.39825244998,
            1425.0
        ],
        "materials": [
            "wallMaterial"
        ]
    },
    {
        "actor_label": "Cube2",
        "actor_location": [
            2064.062858133151,
            3145.1987097423403,
            1278.1265548219749
        ],
        "actor_size": [
            772.5613403473856,
            56.79817083056241,
            540.4770822734922
        ],
        "materials": [
            "windowMaterial"
        ]
    },
    {
        "actor_label": "Cube3",
        "actor_location": [
            917.8830382549095,
            1120.8973663761537,
            1897.2322072462389
        ],
        "actor_size": [
            908.3235035974037,
            25.0,
            644.2902744313196
        ],
        "materials": [
            "windowMaterial"
        ]
    },
    {
        "actor_label": "Cube4",
        "actor_location": [
            456.6075391745257,
            3145.1987097423403,
            546.9619128013908
        ],
        "actor_size": [
            772.5613403473856,
            56.79817083056241,
            540.477082273492
        ],
        "materials": [
            "windowMaterial"
        ]
    },
    {
        "actor_label": "Cube5",
        "actor_location": [
            2066.0055121059486,
            3145.1987097423403,
            517.1931864556486
        ],
        "actor_size": [
            772.5333884916618,
            56.79817083056241,
            540.477082273492
        ],
        "materials": [
            "windowMaterial"
        ]
    },
    {
        "actor_label": "Cube6",
        "actor_location": [
            443.6798059023136,
            3145.1987097423403,
            1302.5005730130424
        ],
        "actor_size": [
            772.5333884916619,
            56.79817083056241,
            540.4770822734922
        ],
        "materials": [
            "windowMaterial"
        ]
    },
    {
        "actor_label": "Cube7",
        "actor_location": [
            917.8830382549098,
            1142.1966804376143,
            1897.2182313183773
        ],
        "actor_size": [
            986.420988489426,
            56.79817083056105,
            722.415711179065
        ],
        "materials": [
            "doorMaterial"
        ]
    },
    {
        "actor_label": "Cube8",
        "actor_location": [
            1282.403188747701,
            3159.4122283778424,
            512.7767932513038
        ],
        "actor_size": [
            703.436401142672,
            703.4084492869479,
            603.4805650747153
        ],
        "materials": [
            "doorMaterial"
        ]
    },
    {
        "actor_label": "Cube9",
        "actor_location": [
            4714.332034503771,
            2849.7336188149534,
            639.6782182369087
        ],
        "actor_size": [
            539.5826228903334,
            619.3292672700545,
            887.4714192275226
        ],
        "materials": [
            "stairMaterial"
        ]
    },
    {
        "actor_label": "Cube10",
        "actor_location": [
            2773.3411971220767,
            2629.025766020606,
            1352.32475584054
        ],
        "actor_size": [
            310.62897265749416,
            537.8216559797402,
            537.8216559797406
        ],
        "materials": [
            "stairMaterial"
        ]
    },
    {
        "actor_label": "Cube11",
        "actor_location": [
            3812.0,
            1579.6991259999998,
            644.284069
        ],
        "actor_size": [
            2425.0,
            3159.3983,
            900.0
        ],
        "materials": [
            "wallMaterial"
        ]
    },
    {
        "actor_label": "Cube12",
        "actor_location": [
            899.0,
            674.699126,
            1936.2840690000003
        ],
        "actor_size": [
            1575.0,
            950.0,
            650.0000000000002
        ],
        "materials": [
            "wallMaterial"
        ]
    },
    {
        "actor_label": "Cube13",
        "actor_location": [
            1312.0,
            1579.6991259999998,
            1612.284069
        ],
        "actor_size": [
            2600.0,
            3159.3983,
            50.0
        ],
        "materials": [
            "roofMaterial"
        ]
    },
    {
        "actor_label": "Cube14",
        "actor_location": [
            3812.0,
            1579.6991259999998,
            1096.284069
        ],
        "actor_size": [
            2425.0,
            3159.3983,
            50.0
        ],
        "materials": [
            "roofMaterial"
        ]
    },
    {
        "actor_label": "Cube15",
        "actor_location": [
            904.0,
            667.699126,
            2271.2840690000003
        ],
        "actor_size": [
            1600.0,
            1000.0,
            50.0
        ],
        "materials": [
            "roofMaterial"
        ]
    }
]